quik_ai/__init__.py
quik_ai/backend.py
quik_ai/engine.py
quik_ai/heads.py
quik_ai/layers.py
quik_ai/losses.py
quik_ai/metrics.py
quik_ai/models.py
quik_ai/optimizers.py
quik_ai/predictors.py
quik_ai/tuners.py
quik_ai/tuning.py
quik_ai-1.3.2.dist-info/LICENSE
quik_ai-1.3.2.dist-info/METADATA
quik_ai-1.3.2.dist-info/WHEEL
quik_ai-1.3.2.dist-info/top_level.txt
quik_ai-1.3.2.dist-info/RECORD
