Metadata-Version: 2.1
Name: quik-ai
Version: 1.3.2
Summary: Quick Unifying Infrastructure Kit for Machine Learning and AI
Home-page: https://github.com/touzov1012/quik-ai
Download-URL: https://github.com/touzov1012/quik-ai/archive/refs/tags/v1.3.2.tar.gz
Author: Aleksandr Touzov
Classifier: Programming Language :: Python :: 3
Classifier: License :: OSI Approved :: Apache Software License
Classifier: Operating System :: OS Independent
Requires-Python: >=3.8
License-File: LICENSE
Requires-Dist: pandas (>=1.3.5)
Requires-Dist: numpy (>=1.21.6)
Requires-Dist: tensorflow (>=2.8.0)
Requires-Dist: tensorflow-probability (>=0.16.0)
Requires-Dist: keras (>=2.8.0)
Requires-Dist: keras-tuner (>=1.2.0)
